[
    {
        "name": "balalt",
        "sprite": "balalt",
        "tiling": "1",
        "color": [
            "0",
            "1"
        ]
    },
    {
        "name": "text_balalt",
        "sprite": "text_balalt",
        "tiling": "-1",
        "color": [
            "0",
            "1"
        ]
    },
    {
        "name": "crystalball",
        "sprite": "crystalball",
        "tiling": "-1",
        "color": [
            "3",
            "0"
        ]
    },
    {
        "name": "fu",
        "sprite": "fu",
        "tiling": "2",
        "color": [
            "3",
            "2"
        ]
    },
    {
        "name": "text_fu",
        "sprite": "text_fu",
        "tiling": "-1",
        "color": [
            "3",
            "1"
        ],
        "active": [
            "3",
            "2"
        ]
    },
    {
        "name": "jaja",
        "sprite": "jeje",
        "tiling": "2",
        "color": [
            "2",
            "3"
        ]
    },
    {
        "name": "text_jeje",
        "sprite": "text_jeje",
        "tiling": "-1",
        "color": [
            "2",
            "2"
        ],
        "active": [
            "2",
            "3"
        ]
    },
    {
        "name": "metronome",
        "sprite": "metronome",
        "tiling": "4",
        "color": [
            "0",
            "3"
        ]
    },
    {
        "name": "babalpha",
        "sprite": "babalpha",
        "color": [
            "0",
            "3"
        ],
        "tiling": "0"
    },
    {
        "name": "debugc",
        "sprite": "debugc",
        "color": [
            "0",
            "3"
        ],
        "tiling": "2"
    },
    {
        "name": "goob",
        "sprite": "goob",
        "color": [
            "4",
            "2"
        ],
        "tiling": "2"
    },
    {
        "name": "feather",
        "sprite": "feather",
        "color": [
            "3",
            "4"
        ],
        "tiling": "-1"
    },
    {
        "name": "text_nuhuh",
        "sprite": "nuhuh",
        "color": [
            "2",
            "2"
        ],
        "tiling": "0"
    },
    {
        "name": "scug",
        "sprite": "scug",
        "color": [
            "0",
            "3"
        ],
        "tiling": "2"
    },
    {
        "name": "text_scug",
        "sprite": "text_scug",
        "color": [
            "0",
            "2"
        ],
        "tiling": "-1"
    },
    {
        "name": "jar",
        "sprite": "jar",
        "color": [
            "4",
            "4"
        ],
        "tiling": "-1"
    },
    {
        "name": "text_jar",
        "sprite": "text_jar",
        "color": [
            "4",
            "4"
        ],
        "tiling": "-1"
    },
    {
        "name": "text_betabeta",
        "sprite": "text_betabeta",
        "color": [
            "5",
            "4"
        ],
        "tiling": "-1"
    },
    {
        "name": "cba",
        "sprite": "cba",
        "color": [
            "0",
            "3"
        ],
        "tiling": "2"
    },
    {
        "name": "text_cba2",
        "sprite": "text_cba",
        "color": [
            "4",
            "1"
        ],
        "tiling": "-1"
    },
    {
        "name": "tplate",
        "sprite": "tplate",
        "color": [
            "0",
            "3"
        ],
        "tiling": "1"
    },
    {
        "name": "knife",
        "sprite": "knife",
        "color": [
            "0",
            "2"
        ],
        "tiling": "-1"
    },
    {
        "name": "debug",
        "sprite": "debug",
        "color": [
            "0",
            "3"
        ],
        "tiling": "-1"
    },
    {
        "name": "text_rw_ascension",
        "sprite": "ascension",
        "color": ["2", "4"],
        "tiling": "-1"
    },
    {
        "name": "text_rw_assistance",
        "sprite": "assistance",
        "color": ["3", "1"],
        "tiling": "-1"
    },
    {
        "name": "text_rw_friendship",
        "sprite": "friendship",
        "color": ["4", "2"],
        "tiling": "-1"
    },
    {
        "name": "text_rw_gluttony",
        "sprite": "gluttony",
        "color": ["6", "2"],
        "tiling": "-1"
    },
    {
        "name": "text_rw_lust",
        "sprite": "lust",
        "color": ["1", "2"],
        "tiling": "-1"
    },
    {
        "name": "text_rw_monk",
        "sprite": "monk",
        "color": ["2", "4"],
        "tiling": "-1"
    },
    {
        "name": "text_rw_survival",
        "sprite": "survival",
        "color": ["0", "3"],
        "tiling": "-1"
    },
    {
        "name": "text_rw_travel",
        "sprite": "travel",
        "color": ["4", "4"],
        "tiling": "-1"
    },
    {
        "name": "text_rw_violence",
        "sprite": "violence",
        "color": ["2", "1"],
        "tiling": "-1"
    },
    {
        "name": "text_rw_wanderer",
        "sprite": "wanderer",
        "color": ["1", "1"],
        "tiling": "-1"
    }
]