[
    {
        "name": "text_say",
        "sprite": "text_say",
        "color": [
		"0",
            "3"
        ],
        "tiling": "-1"
    },
    {
        "name": "text_sparked3",
        "sprite": "text_sparked3",
        "color": [
            "2",
            "3"
        ],
        "tiling": "-1"
    },
    {
        "name": "text_sparked",
        "sprite": "text_sparked",
        "color": [
            "3",
            "1"
        ],
        "tiling": "-1"
    },
    {
        "name": "text_restarted",
        "sprite": "text_restarted",
        "color": [
            "4",
            "1"
        ],
        "tiling": "-1"
    },
    {
        "name": "text_doggo",
        "sprite": "text_doggo",
        "color": [
            "6",
            "1"
        ],
        "tiling": "-1"
},
    {
        "name": "text_defeat2",
        "sprite": "text_defeat2",
        "color": [
            "2",
            "1"
        ],
        "tiling": "-1"
    },
    {
        "name": "groupenemy2",
        "sprite": "groupenemy2",
        "color": [
            "2",
            "1"
        ],
        "tiling": "-1"
    },
    {
        "name": "text_onrow",
        "sprite": "text_onrow",
        "color": [
            "1",
            "4"
        ],
        "tiling": "-1"
    },
    {
        "name": "text_groupwincon",
        "sprite": "text_groupwincon",
        "color": [
            "2",
            "4"
        ],
        "tiling": "-1"
    },
    {
        "name": "text_single",
        "sprite": "text_single",
        "color": [
            "5",
			"2"
        ],
        "tiling": "-1"
    },
    {
        "name": "text_defeat1",
        "sprite": "text_defeat1",
        "color": [
            "2",
            "1"
        ],
        "tiling": "-1"
    },
    {
        "name": "text_onlyone",
        "sprite": "text_onlyone",
        "color": [
            "4",
            "1"
        ],
        "tiling": "-1"
    },
    {
        "name": "text_moving",
        "sprite": "text_moving",
        "color": [
            "5",
            "3"
        ],
        "tiling": "-1"
    },
    {
        "name": "text_gay",
        "sprite": "text_gay",
        "color": [
            "0",
            "3"
        ],
        "tiling": "-1"
    },
    {
        "name": "text_1restarted",
        "sprite": "text_1restarted",
        "color": [
            "4",
            "1"
],
        "tiling": "-1"
    },
    {
        "name": "text_trans",
        "sprite": "text_trans",
        "color": [
            "0",
            "3"
        ],
        "tiling": "-1"
    },
    {
        "name": "text_1below",
        "sprite": "text_1below",
        "color": [
            "0",
            "3"
        ],
        "tiling": "-1"
    },
    {
        "name": "text_leftt",
        "sprite": "text_leftt",
        "color": [
            "1",
            "4"
        ],
        "tiling": "-1"
    },
    {
        "name": "text_isnt",
        "sprite": "text_isnt",
        "color": [
            "0",
            "3"
        ],
		"tiling": "-1"
    },
    {
        "name": "text_doggy",
        "sprite": "text_doggy",
        "color": [
            "6",
            "1"
        ],
        "tiling": "-1"
    },
    {
        "name": "text_enabled",
        "sprite": "text_enabled",
        "color": [
            "5",
            "3"
        ],
        "tiling": "-1"
    },
    {
        "name": "text_spark2",
        "sprite": "text_spark2",
        "color": [
            "4",
            "1"
        ],
        "tiling": "-1"
    },
    {
        "name": "text_color",
        "sprite": "text_color",
        "color": [
            "0",
            "3"
        ],
        "tiling": "-1"
    },
    {
        "name": "text_off",
        "sprite": "text_off",
        "color": [
            "2",
            "2"
        ],
        "tiling": "-1"
    },
    {
        "name": "text_tired",
        "sprite": "text_tired",
        "color": [
			"1",
            "4"
        ],
        "tiling": "-1"
    },
    {
        "name": "text_oncol",
        "sprite": "text_oncol",
        "color": [
            "1",
            "4"
        ],
        "tiling": "-1"
    },
    {
        "name": "text_on2",
        "sprite": "text_on2",
        "color": [
            "5",
            "3"
        ],
        "tiling": "-1"
    },
    {
        "name": "text_vert",
        "sprite": "text_vert",
        "color": [
            "1",
            "4"
        ],
        "tiling": "-1"
    },
    {
        "name": "text_undone",
        "sprite": "text_undone",
        "color": [
            "5",
            "3"
        ],
        "tiling": "-1"
    },
    {
        "name": "text_with",
		"sprite": "text_with",
        "color": [
            "0",
            "3"
        ],
        "tiling": "-1"
    },
    {
        "name": "text_groupenemy2",
        "sprite": "text_groupenemy2",
        "color": [
            "2",
            "1"
        ],
        "tiling": "-1"
    },
    {
        "name": "text_spark",
        "sprite": "text_spark",
        "color": [
            "3",
            "1"
        ],
        "tiling": "-1"
    },
    {
        "name": "text_1besideleft",
        "sprite": "text_1besideleft",
        "color": [
            "0",
            "3"
        ],
        "tiling": "-1"
    },
    {
        "name": "groupenemy1",
        "sprite": "groupenemy1",
        "color": [
            "2",
            "1"
        ],
        "tiling": "-1"
    },
    {
        "name": "text_groupenemy",
		"sprite": "text_groupenemy",
        "color": [
            "2",
            "1"
        ],
        "tiling": "-1"
    },
    {
        "name": "text_horiz",
        "sprite": "text_horiz",
        "color": [
            "1",
            "4"
        ],
        "tiling": "-1"
    },
    {
        "name": "groupenemy",
        "sprite": "groupenemy",
        "color": [
            "2",
            "1"
        ],
        "tiling": "-1"
    },
    {
        "name": "text_upp",
        "sprite": "text_upp",
        "color": [
            "1",
            "4"
        ],
        "tiling": "-1"
    },
    {
        "name": "text_1besideright",
        "sprite": "text_1besideright",
        "color": [
			"0",
            "3"
        ],
        "tiling": "-1"
    },
    {
        "name": "groupwincon",
        "sprite": "groupwincon",
        "color": [
            "2",
            "4"
        ],
        "tiling": "-1"
    },
    {
        "name": "groupextra",
        "sprite": "groupextra",
        "color": [
            "4",
            "1"
        ],
        "tiling": "-1"
    },
    {
        "name": "text_diagto",
        "sprite": "text_diagto",
        "color": [
            "0",
            "3"
        ],
        "tiling": "-1"
    },
    {
        "name": "text_groupplayer2",
        "sprite": "text_groupplayer2",
        "color": [
			"4",
            "1"
        ],
        "tiling": "-1"
    },
    {
        "name": "groupplayer2",
        "sprite": "groupplayer2",
        "color": [
            "4",
            "1"
        ],
        "tiling": "0"
    },
    {
        "name": "text_rightt",
        "sprite": "text_rightt",
        "color": [
            "1",
            "4"
        ],
        "tiling": "-1"
    },
    {
        "name": "thistext",
        "sprite": "thistext",
        "color": [
            "0",
            "3"
        ],
        "tiling": "-1"
    },
    {
        "name": "groupplayer",
        "sprite": "groupplayer",
		"color": [
			"4",
            "1"
        ],
        "tiling": "0"
    },
    {
        "name": "text_downn",
        "sprite": "text_downn",
        "color": [
            "1",
            "4"
        ],
        "tiling": "-1"
    },
    {
        "name": "text_around",
        "sprite": "text_around",
        "color": [
            "0",
            "3"
        ],
        "tiling": "-1"
    },
    {
        "name": "text_sparked2",
        "sprite": "text_sparked2",
        "color": [
            "4",
            "1"
        ],
		"tiling": "-1"
    },
    {
        "name": "text_groupplayer",
        "sprite": "text_groupplayer",
        "color": [
            "4",
            "1"
        ],
        "tiling": "-1"
    },
    {
        "name": "text_spark3",
        "sprite": "text_spark3",
        "color": [
            "2",
            "3"
        ],
        "tiling": "-1"
    },
    {
        "name": "text_nocontrol",
        "sprite": "text_nocontrol",
        "color": [
            "4",
            "1"
        ],
		"tiling": "-1"
    },
    {
        "name": "text_1above",
        "sprite": "text_1above",
        "color": [
            "0",
            "3"
        ],
        "tiling": "-1"
    },
    {
        "name": "text_groupenemy1",
        "sprite": "text_groupenemy1",
        "color": [
            "2",
            "1"
        ],
        "tiling": "-1"
    },
    {
        "name": "text_groupextra",
        "sprite": "text_groupextra",
        "color": [
            "4",
            "1"
        ],
        "tiling": "-1"
    },
    {
		"name": "text_enby",
        "sprite": "text_enby",
        "color": [
            "0",
            "3"
        ],
        "tiling": "-1"
    }
]
