[
    {
        "name": "gk9",
        "sprite": "gabeyk9",
        "color": [
            "1",
            "4"
        ],
        "tiling": "2"
    },
    {
        "name": "justdont",
        "sprite": "justdont",
        "color": [
            "0",
            "4"
        ],
        "tiling": "2"
    },
    {
        "name": "pixel2",
        "sprite": "pixel2",
        "color": [
            "0",
            "3"
        ],
        "tiling": "1"
    },
    {
        "name": "tesho",
        "sprite": "tesho",
        "color": [
            "2",
            "4"
        ],
        "tiling": "2"
    },
    {
        "name": "ryry",
        "sprite": "ryry",
        "color": [
            "1",
            "3"
        ],
        "tiling": "2"
    },
    {
        "name": "glyph_tesho",
        "sprite": "glyph_tesho",
        "color": [
            "2",
            "4"
        ],
        "tiling": "-1"
    },
    {
        "name": "glyph_ryry",
        "sprite": "glyph_ryry",
        "color": [
            "1",
            "3"
        ],
        "tiling": "-1"
    },
    {
        "name": "glyph_moli",
        "sprite": "glyph_moli",
        "color": [
            "1",
            "3"
        ],
        "tiling": "-1"
    },
    {
        "name": "toshu",
        "sprite": "toshu",
        "color": [
            "2",
            "4"
        ],
        "tiling": "2"
    },
    {
        "name": "token",
        "sprite": "token",
        "color": [
            "6",
            "2"
        ],
        "tiling": "-1"
    },
    {
        "name": "btoken",
        "sprite": "btoken",
        "color": [
            "6",
            "2"
        ],
        "tiling": "-1"
    },
    {
        "name": "moli",
        "sprite": "moli",
        "color": [
            "1",
            "3"
        ],
        "tiling": "2"
    },
    {
        "name": "glyph_gk9",
        "sprite": "glyph_gk9",
        "color": [
            "1",
            "4"
        ],
        "tiling": "-1"
    },
    {
        "name": "genemy",
        "sprite": "groupenemy",
        "color": [
            "2",
            "2"
        ],
        "tiling": "-1"
    },
    {
        "name": "genemy1",
        "sprite": "groupenemy1",
        "color": [
            "2",
            "2"
        ],
        "tiling": "-1"
    },
    {
        "name": "genemy2",
        "sprite": "groupenemy2",
        "color": [
            "2",
            "2"
        ],
        "tiling": "-1"
    },
    {
        "name": "gextra",
        "sprite": "groupextra",
        "color": [
            "4",
            "1"
        ],
        "tiling": "-1"
    },
    {
        "name": "gplayer",
        "sprite": "groupplayer",
        "color": [
            "4",
            "1"
        ],
        "tiling": "0"
    },
    {
        "name": "gplayer2",
        "sprite": "groupplayer2",
        "color": [
            "4",
            "1"
        ],
        "tiling": "0"
    },
    {
        "name": "gwincon",
        "sprite": "groupwincon",
        "color": [
            "2",
            "4"
        ],
        "tiling": "-1"
    },
    {
        "name": "ion",
        "sprite": "ion",
        "color": [
            "3",
            "3"
        ],
        "tiling": "-1"
    },
    {
        "name": "jaejae",
        "sprite": "jaejae",
        "color": [
            "4",
            "2"
        ],
        "tiling": "2"
    },
    {
        "name": "basbii",
        "sprite": "basbii",
        "color": [
            "0",
            "3"
        ],
        "tiling": "0"
    },
    {
        "name": "text_basbii",
        "sprite": "text_basbii",
        "color": [
            "0",
            "3"
        ],
        "tiling": "-1"
    },
    {
        "name": "kescii",
        "sprite": "kescii",
        "color": [
            "2",
            "2"
        ],
        "tiling": "0"
    },
    {
        "name": "text_kescii",
        "sprite": "text_kescii",
        "color": [
            "2",
            "2"
        ],
        "tiling": "-1"
    },
    {
        "name": "flasgii",
        "sprite": "flasgii",
        "color": [
            "2",
            "4"
        ],
        "tiling": "-1"
    },
    {
        "name": "text_flasgii",
        "sprite": "text_flasgii",
        "color": [
            "2",
            "4"
        ],
        "tiling": "-1"
    },
    {
        "name": "fosfii",
        "sprite": "fosfii",
        "color": [
            "5",
            "2"
        ],
        "tiling": "0"
    },
    {
        "name": "text_fosfii",
        "sprite": "text_fosfii",
        "color": [
            "5",
            "2"
        ],
        "tiling": "-1"
    },
    {
        "name": "rocsii",
        "sprite": "rocsii",
        "color": [
            "6",
            "2"
        ],
        "tiling": "-1"
    },
    {
        "name": "text_rocsii",
        "sprite": "text_rocsii",
        "color": [
            "6",
            "2"
        ],
        "tiling": "-1"
    },
    {
        "name": "jisjii",
        "sprite": "jisjii",
        "color": [
            "2",
            "3"
        ],
        "tiling": "0"
    },
    {
        "name": "text_jisjii",
        "sprite": "text_jisjii",
        "color": [
            "2",
            "3"
        ],
        "tiling": "-1"
    },
    {
        "name": "istii",
        "sprite": "istii",
        "color": [
            "1",
            "4"
        ],
        "tiling": "0"
    },
    {
        "name": "text_istii",
        "sprite": "text_istii",
        "color": [
            "1",
            "4"
        ],
        "tiling": "-1"
    },
    {
        "name": "walsii",
        "sprite": "walsii",
        "color": [
            "0",
            "1"
        ],
        "tiling": "-1"
    },
    {
        "name": "text_walsii",
        "sprite": "text_walsii",
        "color": [
            "0",
            "1"
        ],
        "tiling": "-1"
    },
    {
        "name": "text_tilsii",
        "sprite": "text_tilsii",
        "color": [
            "0",
            "0"
        ],
        "tiling": "-1"
    },
    {
        "name": "tilsii",
        "sprite": "tilsii",
        "color": [
            "0",
            "0"
        ],
        "tiling": "-1"
    },
    {
        "name": "text_mescii",
        "sprite": "text_mescii",
        "color": [
            "3",
            "1"
        ],
        "tiling": "-1"
    },
    {
        "name": "mescii",
        "sprite": "mescii",
        "color": [
            "3",
            "1"
        ],
        "tiling": "0"
    },
    {
        "name": "text_grascii",
        "sprite": "text_grascii",
        "color": [
            "5",
            "1"
        ],
        "tiling": "-1"
    },
    {
        "name": "grascii",
        "sprite": "grascii",
        "color": [
            "5",
            "1"
        ],
        "tiling": "-1"
    },
    {
        "name": "text_watsii",
        "sprite": "text_watsii",
        "color": [
            "1",
            "3"
        ],
        "tiling": "-1"
    },
    {
        "name": "watsii",
        "sprite": "watsii",
        "color": [
            "1",
            "3"
        ],
        "tiling": "-1"
    },
    {
        "name": "balscii",
        "sprite": "balscii",
        "color": [
            "0",
            "1"
        ],
        "tiling": "0"
    },
    {
        "name": "text_balscii",
        "sprite": "text_balscii",
        "color": [
            "0",
            "1"
        ],
        "tiling": "-1"
    },
    {
        "name": "onethem",
        "sprite": "onethem",
        "color": [
            "5",
            "3"
        ],
        "tiling": "-1"
    },
    {
        "name": "ixor",
        "sprite": "ixor",
        "color": [
            "0",
            "3"
        ],
        "tiling": "0"
    },
    {
        "name": "ba",
        "sprite": "ba",
        "color": [
            "0",
            "3"
        ],
        "tiling": "-1"
    },
    {
        "name": "catile_h",
        "sprite": "catile_h",
        "color": [
            "5",
            "2"
        ],
        "tiling": "-1"
    },
    {
        "name": "catext_h",
        "sprite": "catext_h",
        "color": [
            "5",
            "2"
        ],
        "tiling": "-1"
    },
    {
        "name": "whatesho",
        "sprite": "whatesho",
        "color": [
            "2",
            "4"
        ],
        "tiling": "-1"
    },
    {
        "name": "text_whatesho",
        "sprite": "text_whatesho",
        "color": [
            "2",
            "4"
        ],
        "tiling": "-1"
    },
    {
        "name": "gigi",
        "sprite": "gigi",
        "color": [
            "1",
            "2"
        ],
        "tiling": "-1"
    },
    {
        "name": "jk8",
        "sprite": "jk8",
        "color": [
            "3",
            "1"
        ],
        "tiling": "2"
    },
    {
        "name": "text_ba2",
        "sprite": "text_ba",
        "color": [
            "0",
            "3"
        ],
        "tiling": "-1"
    },
    {
        "name": "text_catext_h",
        "sprite": "text_catext_h",
        "color": [
            "5",
            "2"
        ],
        "tiling": "-1"
    },
    {
        "name": "text_catile_h",
        "sprite": "text_catile_h",
        "color": [
            "5",
            "2"
        ],
        "tiling": "-1"
    },
    {
        "name": "text_gigi",
        "sprite": "text_gigi",
        "color": [
            "1",
            "2"
        ],
        "tiling": "-1"
    },
    {
        "name": "text_gk9",
        "sprite": "text_gk9",
        "color": [
            "1",
            "4"
        ],
        "tiling": "-1"
    },
    {
        "name": "text_ixor",
        "sprite": "text_ixor",
        "color": [
            "0",
            "3"
        ],
        "tiling": "-1"
    },
    {
        "name": "text_jaejae",
        "sprite": "text_jaejae",
        "color": [
            "4",
            "2"
        ],
        "tiling": "-1"
    },
    {
        "name": "text_jk8",
        "sprite": "text_jk8",
        "color": [
            "3",
            "1"
        ],
        "tiling": "-1"
    },
    {
        "name": "text_justdont",
        "sprite": "text_justdont",
        "color": [
            "6",
            "4"
        ],
        "tiling": "-1"
    },
    {
        "name": "text_moli",
        "sprite": "text_moli",
        "color": [
            "1",
            "3"
        ],
        "tiling": "-1"
    },
    {
        "name": "text_pixel2",
        "sprite": "text_pixel2",
        "color": [
            "0",
            "3"
        ],
        "tiling": "-1"
    },
    {
        "name": "text_ryry",
        "sprite": "text_ryry",
        "color": [
            "1",
            "3"
        ],
        "tiling": "-1"
    },
    {
        "name": "text_toshu",
        "sprite": "text_toshu",
        "color": [
            "2",
            "4"
        ],
        "tiling": "-1"
    },
    {
        "name": "text_tesho",
        "sprite": "text_tesho",
        "color": [
            "2",
            "4"
        ],
        "tiling": "-1"
    },
    {
        "name": "ktoken",
        "sprite": "ktoken",
        "color": [
            "6",
            "2"
        ],
        "tiling": "-1"
    },
    {
        "name": "jtoken",
        "sprite": "jtoken",
        "color": [
            "6",
            "2"
        ],
        "tiling": "-1"
    },
    {
        "name": "mtoken",
        "sprite": "mtoken",
        "color": [
            "6",
            "2"
        ],
        "tiling": "-1"
    },
    {
        "name": "ftoken",
        "sprite": "ftoken",
        "color": [
            "6",
            "2"
        ],
        "tiling": "-1"
    },
    {
        "name": "wallboard",
        "sprite": "wallboard",
        "color": [
            "0",
            "1"
        ],
        "tiling": "1"
    },
    {
        "name": "wk7",
        "sprite": "wk7",
        "color": [
            "4",
            "1"
        ],
        "tiling": "2"
    },
    {
        "name": "text_wk7",
        "sprite": "text_wk7",
        "color": [
            "4",
            "1"
        ],
        "tiling": "-1"
    },
    {
        "name": "text_\u27d0\u26e2\u26ec\u26d2",
        "sprite": "text_27d0_26e2_26ec_26d2",
        "color": [
            "0",
            "3"
        ],
        "tiling": "-1"
    },
    {
        "name": "text_\u27d0",
        "sprite": "text_27d0",
        "color": [
            "0",
            "3"
        ],
        "tiling": "-1"
    },
    {
        "name": "text_\u26e2",
        "sprite": "text_26e2",
        "color": [
            "0",
            "3"
        ],
        "tiling": "-1"
    },
    {
        "name": "text_\u26ec",
        "sprite": "text_26ec",
        "color": [
            "0",
            "3"
        ],
        "tiling": "-1"
    },
    {
        "name": "text_\u26d2",
        "sprite": "text_26d2",
        "color": [
            "0",
            "3"
        ],
        "tiling": "-1"
    },
    {
        "name": "fo_tl",
        "sprite": "fe",
        "color": [
            "5",
            "3"
        ],
        "tiling": "0"
    },
    {
        "name": "fo_bl",
        "sprite": "fi",
        "color": [
            "5",
            "4"
        ],
        "tiling": "0"
    },
    {
        "name": "fo_tr",
        "sprite": "fo",
        "color": [
            "5",
            "2"
        ],
        "tiling": "0"
    },
    {
        "name": "fo_br",
        "sprite": "fum",
        "color": [
            "5",
            "1"
        ],
        "tiling": "0"
	},
	{
        "name": "floog",
        "sprite": "floog",
        "color": [
            "2",
            "4"
        ],
        "tiling": "-1"
    },
    {
        "name": "thes",
        "sprite": "thase",
        "color": [
            "0",
            "3"
        ],
        "tiling": "-1"
    },
    {
        "name": "jsykutjryj",
        "sprite": "jsykutjryj",
        "color": [
            "6",
            "1"
        ],
        "tiling": "2"
    },
    {
        "name": "text_jsykutjryj",
        "sprite": "text_jsykutjryj",
        "color": [
            "6",
            "1"
        ],
        "tiling": "-1"
    },
    {
        "name": "glyph_i2",
        "sprite": "glyph_i2",
        "color": [
            "1",
            "4"
        ],
        "tiling": "-1"
    },
    {
        "name": "glyph_traitrai",
        "sprite": "glyph_traitrai",
        "color": [
            "4",
            "4"
        ],
        "tiling": "-1"
    },
    {
        "name": "flaglitch",
        "sprite": "flaglitch",
        "color": [
            "0",
            "3"
        ],
        "tiling": "-1"
    }
]
